grpc_fastapi_client_gen/__init__.py
grpc_fastapi_client_gen/client.j2
grpc_fastapi_client_gen/client_generator.py
grpc_fastapi_client_gen/main.py
grpc_fastapi_client_gen/utils.py
grpc_fastapi_gateway/__init__.py
grpc_fastapi_gateway/config.py
grpc_fastapi_gateway/context.py
grpc_fastapi_gateway/decorators.py
grpc_fastapi_gateway/example_usage.py
grpc_fastapi_gateway/exceptions.py
grpc_fastapi_gateway/gateway.py
grpc_fastapi_gateway/hypercorn_h2.patch
grpc_fastapi_gateway/patch.py
grpc_fastapi_gateway/request.py
grpc_fastapi_gateway/response.py
grpc_fastapi_gateway/test_patch.py
grpc_fastapi_gateway/types.py
grpc_fastapi_gateway/typings.py
grpc_fastapi_gateway/utils/__init__.py
grpc_fastapi_gateway/utils/request.py
grpc_fastapi_gateway/utils/validation.py
protobuf_pydantic_gen/__init__.py
protobuf_pydantic_gen/any_type_transformer.py
protobuf_pydantic_gen/config.py
protobuf_pydantic_gen/constants.py
protobuf_pydantic_gen/examples.py
protobuf_pydantic_gen/ext.py
protobuf_pydantic_gen/generator.py
protobuf_pydantic_gen/main.py
protobuf_pydantic_gen/main_new.py
protobuf_pydantic_gen/message_processor.py
protobuf_pydantic_gen/models.py
protobuf_pydantic_gen/pydantic_pb2.py
protobuf_pydantic_gen/pydantic_pb2.pyi
protobuf_pydantic_gen/pydantic_pb2_grpc.py
protobuf_pydantic_gen/service_processor.py
protobuf_pydantic_gen/template.j2
protobuf_pydantic_gen/template_renderer.py
protobuf_pydantic_gen/type_mapper.py
protobuf_pydantic_gen/utils.py
protobuf_pydantic_gen-0.1.8.dist-info/licenses/LICENSE
protobuf_pydantic_gen-0.1.8.dist-info/METADATA
protobuf_pydantic_gen-0.1.8.dist-info/WHEEL
protobuf_pydantic_gen-0.1.8.dist-info/entry_points.txt
protobuf_pydantic_gen-0.1.8.dist-info/top_level.txt
protobuf_pydantic_gen-0.1.8.dist-info/RECORD
