Metadata-Version: 2.4
Name: protobuf-pydantic-gen
Version: 0.1.8
Summary: A tool for converting between Pydantic models and Protobuf messages, specifically enabling the generation of Pydantic BaseModel classes from .proto files.
Author-email: geebytes <vforfreedom96@gmail.com>
License: Apache-2.0
Requires-Python: >=3.9
License-File: LICENSE
Requires-Dist: grpcio>=1.50.0
Requires-Dist: grpcio-tools>=1.50.0
Requires-Dist: protobuf<7.0.0,>=4.21.12
Requires-Dist: pydantic>=2.4.1
Requires-Dist: jinja2>=3.0.0
Requires-Dist: peewee>=3.17.5
Requires-Dist: sqlmodel>=0.0.19
Requires-Dist: inflection>=0.5.1
Requires-Dist: pydantic-core>=2.20.0
Requires-Dist: annotated-types>=0.7.0
Requires-Dist: autopep8>=2.3.1
Requires-Dist: fastapi>=0.115.12
Requires-Dist: starlette>=0.46.2
Requires-Dist: hypercorn==0.17.3
Requires-Dist: googleapis-common-protos>=1.70.0
Requires-Dist: sse-starlette>=2.3.6
Requires-Dist: brotli>=1.1.0
Requires-Dist: zstandard>=0.23.0
Requires-Dist: patchy>=2.9.0
Requires-Dist: granian>=2.3.4
Requires-Dist: patch-ng>=1.18.1
Requires-Dist: httpx>=0.28.1
Requires-Dist: websockets>=15.0.1
Requires-Dist: pytest>=8.4.1
Requires-Dist: pytest-asyncio>=1.0.0
Requires-Dist: pydantic-settings>=2.10.1
Dynamic: license-file
